py_builder_signing_sdk/__init__.py
py_builder_signing_sdk/config.py
py_builder_signing_sdk/sdk_types.py
py_builder_signing_sdk/signer.py
py_builder_signing_sdk/http_helpers/__init__.py
py_builder_signing_sdk/http_helpers/helpers.py
py_builder_signing_sdk/signing/__init__.py
py_builder_signing_sdk/signing/hmac.py
tests/__init__.py
tests/test_config.py
tests/test_signer.py
tests/signing/__init__.py
tests/signing/test_hmac.py
py_builder_signing_sdk-0.0.1.dist-info/METADATA
py_builder_signing_sdk-0.0.1.dist-info/WHEEL
py_builder_signing_sdk-0.0.1.dist-info/top_level.txt
py_builder_signing_sdk-0.0.1.dist-info/RECORD
