Metadata-Version: 2.4
Name: py_builder_signing_sdk
Version: 0.0.1
Summary: Python builder signing sdk
Home-page: https://github.com/Polymarket/py-builder-signing-sdk
Author: Polymarket Engineering
Author-email: engineering@polymarket.com
Maintainer: Polymarket Engineering
Maintainer-email: engineering@polymarket.com
Project-URL: Bug Tracker, https://github.com/Polymarket/py-builder-signing-sdk/issues
Classifier: Programming Language :: Python :: 3
Classifier: License :: OSI Approved :: MIT License
Classifier: Operating System :: OS Independent
Requires-Python: >=3.11
Requires-Dist: python-dotenv
Requires-Dist: requests
Dynamic: author
Dynamic: author-email
Dynamic: classifier
Dynamic: description
Dynamic: description-content-type
Dynamic: home-page
Dynamic: maintainer
Dynamic: maintainer-email
Dynamic: project-url
Dynamic: requires-dist
Dynamic: requires-python
Dynamic: summary
